containers/__init__.py
containers/apache.py
containers/deno.py
containers/mongo.py
containers/mongoseeder.py
containers/nginx.py
containers/node.py
containers/phpfpm.py
containers/python.py
containers/redis.py
containers/sql.py
tests/__init__.py
tests/project_test.py
tests/response_test.py
tests/validate_test.py
denv_creator-0.0.1.dist-info/LICENSE.txt
denv_creator-0.0.1.dist-info/METADATA
denv_creator-0.0.1.dist-info/WHEEL
denv_creator-0.0.1.dist-info/top_level.txt
denv_creator-0.0.1.dist-info/RECORD
