Metadata-Version: 2.1
Name: denv-creator
Version: 0.0.1
Summary: Simple python script to create every file and configurations for multiple docker containers 
Home-page: https://github.com/ebebbington/denv-creator
Author: Edward Bebbinngton
Author-email: EdwardSBebbington@hotmail.com
License: UNKNOWN
Platform: UNKNOWN
Classifier: Programming Language :: Python :: 3
Classifier: License :: OSI Approved :: MIT License
Classifier: Operating System :: OS Independent
Requires-Python: >=3.6
